pipelines/__init__.py
pipelines/__version__.py
pipelines/_base.py
pipelines/py.typed
async_pipelines-0.1.0.dist-info/LICENSE
async_pipelines-0.1.0.dist-info/METADATA
async_pipelines-0.1.0.dist-info/WHEEL
async_pipelines-0.1.0.dist-info/top_level.txt
async_pipelines-0.1.0.dist-info/RECORD
